pg_common/__init__.py
pg_common/conf.py
pg_common/date.py
pg_common/decorator.py
pg_common/func.py
pg_common/gm.py
pg_common/http.py
pg_common/singleton.py
pg_common/tunnel.py
pg_common/util.py
pg_common-1.3.0.dist-info/METADATA
pg_common-1.3.0.dist-info/WHEEL
pg_common-1.3.0.dist-info/top_level.txt
pg_common-1.3.0.dist-info/RECORD
