Metadata-Version: 2.1
Name: pg_common
Version: 1.3.0
Summary: python game: common lib
Author: baozilaji@gmail.com
Requires-Python: >=3.9
Requires-Dist: sshtunnel ==0.4.0
Requires-Dist: redis ==4.6.0
Requires-Dist: prettytable ==3.9.0
Requires-Dist: aiohttp ==3.8.6
Requires-Dist: aiodns ==3.1.1
Requires-Dist: pycryptodome ==3.19.0
Requires-Dist: pymysql ==1.1.0
Requires-Dist: pymongo ==4.7.2
Requires-Dist: requests ==2.28.2
Requires-Dist: pydantic ==1.10.11
